lightparser/__init__.py
lightparser/item.py
lightparser/output.py
lightparser-0.1.4.dist-info/METADATA
lightparser-0.1.4.dist-info/WHEEL
lightparser-0.1.4.dist-info/entry_points.txt
lightparser-0.1.4.dist-info/top_level.txt
lightparser-0.1.4.dist-info/RECORD
